nerdd_kafka/__init__.py
nerdd_kafka/__main__.py
nerdd_kafka/kafka_server.py
nerdd_kafka/serialization/__init__.py
nerdd_kafka/serialization/json_encoder.py
nerdd_kafka/serialization/mol_serializer.py
nerdd_kafka/serialization/registry.py
nerdd_kafka/serialization/serializer.py
tests/__init__.py
tests/conftest.py
tests/test_kafka_server_atom_property_predictor.py
tests/test_kafka_server_initialization.py
tests/test_kafka_server_molecule_property_predictor.py
tests/steps/__init__.py
tests/steps/mocked_kafka.py
tests/steps/molecules.py
tests/steps/records.py
nerdd_kafka-0.2.1.dist-info/LICENSE
nerdd_kafka-0.2.1.dist-info/METADATA
nerdd_kafka-0.2.1.dist-info/WHEEL
nerdd_kafka-0.2.1.dist-info/entry_points.txt
nerdd_kafka-0.2.1.dist-info/top_level.txt
nerdd_kafka-0.2.1.dist-info/RECORD
