Metadata-Version: 2.1
Name: nerdd-kafka
Version: 0.2.1
Summary: Run a NERDD module as a Kafka service
Home-page: https://github.com/molinfo-vienna/nerdd-kafka
Maintainer: Steffen Hirte
Maintainer-email: steffen.hirte@univie.ac.at
License-File: LICENSE
Requires-Dist: rdkit >=2022.3.3
Requires-Dist: kafka-python ==2.0.2
Requires-Dist: nerdd-module >=0.2.0
Requires-Dist: pandas >=1.2.1
Requires-Dist: pyyaml ~=6.0
Requires-Dist: filetype ~=1.2.0
Requires-Dist: rich-click >=1.7.1
Requires-Dist: stringcase ~=1.2.0
Requires-Dist: numpy
Requires-Dist: simplejson >=3
Provides-Extra: dev
Provides-Extra: docs
Requires-Dist: mkdocs ; extra == 'docs'
Requires-Dist: mkdocs-material ; extra == 'docs'
Provides-Extra: test
Requires-Dist: pytest ; extra == 'test'
Requires-Dist: pytest-cov ; extra == 'test'
Requires-Dist: pytest-asyncio ; extra == 'test'
Requires-Dist: pytest-bdd ; extra == 'test'
Requires-Dist: pytest-mock ; extra == 'test'
Requires-Dist: pytest-watch ; extra == 'test'
Requires-Dist: hypothesis ; extra == 'test'
Requires-Dist: hypothesis-rdkit ; extra == 'test'
